{"schemaVersion":"kfc_portal_schema_v1","generatedAt":"2026-07-21T18:29:33.645500+00:00","type":"news","id":"cand-candidate_b74fd3b2e78b6e8c4b8b1a6d","item":{"id":"cand-candidate_b74fd3b2e78b6e8c4b8b1a6d","type":"news","title":"Uhubctl – control USB power per-port on smart USB hubs","sourceId":"github.com","status":"new","publishedAt":"2026-07-22T01:09:37","updatedAt":"2026-07-21T18:07:09.395077Z","summary":"Article URL: https://github.com/mvp/uhubctl Comments URL: https://news.ycombinator.com/item?id=48995149 Points: 3 # Comments: 0","articleId":"","url":"https://github.com/mvp/uhubctl"}}