{"schemaVersion":"kfc_portal_schema_v1","generatedAt":"2026-07-24T19:05:21.018227+00:00","type":"news","id":"news_b3934cb919b05f979ccc","item":{"id":"news_b3934cb919b05f979ccc","type":"news","title":"从尝鲜变为必需：Bloomreach最新消费者调研显示购物者如今更偏爱AI工具","sourceId":"martechseries.com","status":"new","publishedAt":"2026-07-24T19:41:14","updatedAt":"2026-07-24T18:21:55.283344Z","summary":"AI个性化公司Bloomreach发布了对4000名美国和英国消费者进行的调研《AI是否正在取代你的品牌？》。结果显示，过去一年AI在购物领域的采用急剧加速，已从尝鲜变为必需。调研还表明，购物行为已越过临界点：若被迫选择，更多消费者愿意通过AI工具而非品牌官网购物。Bloomreach的Raj De Datta表示：消费者不再只是尝试AI，而是在依赖它，并乐在其中。","articleId":"","url":"https://martechseries.com/predictive-ai/ai-platforms-machine-learning/from-novelty-to-necessity-new-bloomreach-consumer-survey-finds-shoppers-now-prefer-ai-tools-to-shop"}}