{"schemaVersion":"kfc_portal_schema_v1","generatedAt":"2026-07-24T21:05:20.507316+00:00","type":"news","id":"news_8637d39e429b07a96d22","item":{"id":"news_8637d39e429b07a96d22","type":"news","title":"乌克兰使用荷兰Ruta Block 1巡航导弹的证据浮出水面","sourceId":"twz.com","status":"new","publishedAt":"2026-07-25T00:46:44","updatedAt":"2026-07-24T19:11:02.522483Z","summary":"这款低成本导弹首次投入实战，凸显乌克兰正加速向更具能力、可大规模量产、远程打击能力的方向转变。","articleId":"","url":"https://twz.com/news-features/evidence-of-ukraine-using-dutch-ruta-block-1-cruise-missiles-emerges"}}