{"schemaVersion":"kfc_portal_schema_v1","generatedAt":"2026-07-16T04:47:53.619501+00:00","type":"news","id":"news_26238fd1153563dbb848","item":{"id":"news_26238fd1153563dbb848","type":"news","title":"国家统计局：我国平均每天生产芯片超过 15 亿块","sourceId":"ithome.com","status":"watch_only","publishedAt":"2026-07-15T15:12:26","updatedAt":"2026-07-15T07:35:53.655583Z","summary":"IT之家 7 月 15 日消息，国家统计局新闻发言人、国民经济综合统计司负责人王冠华回应记者提问时表示，经过多年的布局和发展，我国新兴产业逐步发展壮大、积厚成势。 上半年规模以上高技术制造业增加值、数字产品制造业增加值分别增长 13.3% 和 12.3%，比一季度都有所加快。特别是全球人工智能技术变革带来的高端算力芯片和存储芯片的需求爆发，上半年我国规模以上工业企业的集成电路产量增长 23.1%，产量规模达到 2798 亿块，这个数字非常庞大， 换算下来平均每天生产集成电路超过 15 亿块 。 官方表示， 集成电路就是我们平时说的芯片 ，它广泛应用于智能装备、电子产品当中，每天超过 15 亿块芯片的产出，不仅是数字的更新，更是中国半导体产业发展动力的生动写照。 据IT之家此前报道，国家统计局初步测算，今年上半年以高端制造、数字经济、现代服务为代表的新动能（不包括对传统行业的改造升级） 对经济增长的贡献率超过四成 。 数据显示，今年上半年，全国规模以上工业增加值同比增长 5.4%。分三大门类看，采矿业增加值同比增长 3.6%，制造业增长 5.6%，电力、热力、燃气及水生产和供应业增长 5.5%。分产品看，3D 打印设备、锂离子电池、工业机器人产品产量同比分别增长 48.5%、39.3%、28.0%。","articleId":"","url":"https://ithome.com/0/977/023.htm"}}